remode/__init__.py
remode/_version.py
remode/remode.py
remode-0.1.1.dist-info/licenses/LICENSE
remode-0.1.1.dist-info/METADATA
remode-0.1.1.dist-info/WHEEL
remode-0.1.1.dist-info/top_level.txt
remode-0.1.1.dist-info/RECORD
