Metadata-Version: 2.4
Name: ReMoDe
Version: 0.1.1
Summary: Recursive Mode Detection for ordinal data
Author-email: Javier Garcia-Bernardo <j.garciabernardo@uu.nl>, Madlen Hoffstadt <m.f.hoffstadt@uva.nl>, Han van der Maas <h.l.j.vanderMaas@uva.nl>
License: MIT License
Project-URL: homepage, https://github.com/sodascience/remode
Project-URL: repository, https://github.com/sodascience/remode
Keywords: mode detection,remode,ordinal data,modality,maximum detection
Classifier: License :: OSI Approved :: MIT License
Classifier: Programming Language :: Python :: 3
Classifier: Programming Language :: Python :: 3.8
Classifier: Programming Language :: Python :: 3.9
Classifier: Programming Language :: Python :: 3.10
Classifier: Programming Language :: Python :: 3.11
Classifier: Programming Language :: Python :: 3.12
Classifier: Operating System :: OS Independent
Requires-Python: >=3.8
License-File: LICENSE
Requires-Dist: numpy
Requires-Dist: matplotlib
Requires-Dist: pandas
Requires-Dist: scipy
Provides-Extra: test
Requires-Dist: ruff; extra == "test"
Requires-Dist: pytest; extra == "test"
Requires-Dist: mypy; extra == "test"
Dynamic: license-file
